pdschema/__init__.py
pdschema/columns.py
pdschema/functions.py
pdschema/schema.py
pdschema/types.py
pdschema/validators.py
pdschema-0.1.3.dist-info/LICENSE
pdschema-0.1.3.dist-info/METADATA
pdschema-0.1.3.dist-info/WHEEL
pdschema-0.1.3.dist-info/RECORD
