Metadata-Version: 2.3
Name: pdschema
Version: 0.1.3
Summary: A Python library for validating pandas DataFrames using schemas
License: MIT
Keywords: pandas,schema,validation,dataframe,pyarrow
Author: pdschema contributors
Requires-Python: >=3.12,<4.0
Classifier: Development Status :: 4 - Beta
Classifier: Intended Audience :: Developers
Classifier: License :: OSI Approved :: MIT License
Classifier: Programming Language :: Python :: 3
Classifier: Programming Language :: Python :: 3.12
Classifier: Programming Language :: Python :: 3.13
Classifier: Programming Language :: Python :: 3.10
Classifier: Programming Language :: Python :: 3.11
Classifier: Programming Language :: Python :: 3.8
Classifier: Programming Language :: Python :: 3.9
Classifier: Topic :: Software Development :: Libraries :: Python Modules
Requires-Dist: pandas (>=1.3.0)
Requires-Dist: pyarrow (>=7.0.0)
Project-URL: Documentation, https://github.com/inquilabee/pdschema#readme
Project-URL: Repository, https://github.com/inquilabee/pdschema
